pyftpd_sink/__init__.py
pyftpd_sink/__init___test.py
pyftpd_sink-0.4.1.dist-info/DESCRIPTION.rst
pyftpd_sink-0.4.1.dist-info/METADATA
pyftpd_sink-0.4.1.dist-info/RECORD
pyftpd_sink-0.4.1.dist-info/WHEEL
pyftpd_sink-0.4.1.dist-info/entry_points.txt
pyftpd_sink-0.4.1.dist-info/metadata.json
pyftpd_sink-0.4.1.dist-info/top_level.txt
